b_labs_models/__init__.py
b_labs_models/morphology.py
b_labs_models/segmentation.py
b_labs_models/settings.py
b_labs_models/tokenization.py
b_labs_models/data/part-of-speech.crfsuite
b_labs_models/data/sentence-segmentation-model.crfsuite
b_labs_models/data/tokenization-model.crfsuite
b_labs_models/tests/__init__.py
b_labs_models/tests/test_pos_tagger.py
b_labs_models/tests/test_segmentation.py
b_labs_models/tests/test_tokenizer.py
b_labs_models-2017.8.21.dist-info/DESCRIPTION.rst
b_labs_models-2017.8.21.dist-info/METADATA
b_labs_models-2017.8.21.dist-info/RECORD
b_labs_models-2017.8.21.dist-info/WHEEL
b_labs_models-2017.8.21.dist-info/metadata.json
b_labs_models-2017.8.21.dist-info/top_level.txt
